{
  "schemaVersion": 1,
  "bucket": "40",
  "plugins": [
    {
      "id": "com.locus.sample.unity-workflow",
      "name": "Unity Workflow Tools",
      "summary": "Provides workflow helpers for repeated Unity editor tasks.",
      "author": "Locus Test",
      "tags": [
        "workflow",
        "unity",
        "automation"
      ],
      "latestVersion": "0.1.0",
      "updatedAt": "2026-06-07T22:27:59Z",
      "icon": {
        "type": "url",
        "url": "https://raw.githubusercontent.com/r1n7aro/locus-plugin-test-workflow-tools/main/icon.svg"
      },
      "compatibility": {
        "projectIndependent": true,
        "minLocusVersion": "0.3.2"
      },
      "stats": [
        {
          "id": "githubStars",
          "label": "Stars",
          "value": 0
        },
        {
          "id": "releaseDownloads",
          "label": "Release downloads",
          "value": 0
        }
      ]
    }
  ]
}
